{"CSP": "AWS", "data_type": "logs", "error": null, "governance_data": {"log_1": "Application started successfully.", "log_2": "Collecting system metrics.", "log_3": "Metrics collected successfully.", "log_4": "Sending data to API Gateway.", "log_5": "Data sent successfully.", "log_6": "Error handling and logging mechanism operational.", "log_7": "System monitoring and logging active.", "log_8": "Routine check completed successfully.", "log_9": "No errors detected in the last cycle.", "log_10": "All systems functional."}, "log_id": "a2f46519-37d5-4d89-84dc-71deb5169726", "service_name": "cna-app", "timestamps": {"cna_timestamp": "2024-09-06T15:39:35.198014+00:00", "RG_1_API_Gateway_timestamp": "2024-09-06T15:39:35.215645+00:00", "RG_1_SQS_Forwarder_timestamp": "2024-09-06T15:39:35.298698+00:00", "RG_GOV_IMS_API_Gateway_timestamp": "2024-09-06T15:39:35.999003+00:00", "RG_GOV_IMS_Converter_timestamp": "2024-09-06T15:39:36.525867+00:00", "RG_GOV_IMS_Archiver_timestamp": "2024-09-06T15:39:36.608669+00:00"}}