{"CSP": "IBM", "data_type": "metrics", "error": null, "governance_data": {"memory_usage": 36.2, "cpu_usage": 55.9, "disk_usage": 4.2, "bytes_sent": 4835307, "bytes_recv": 12875257, "additional_metric_1": "value_1", "additional_metric_2": "value_2"}, "log_id": "37e95b04-8cc8-4ace-b296-d769697456c2", "service_name": "cna-app", "timestamps": {"cna_timestamp": "2024-08-12T17:39:38.683507+00:00", "RG_GOV_IMS_API_Gateway_timestamp": "2024-08-12T17:39:38.762950+00:00", "RG_GOV_IMS_Converter_timestamp": "2024-08-12T17:39:38.840819+00:00", "RG_GOV_IMS_Archiver_timestamp": "2024-08-12T17:39:38.920308+00:00"}}