{"CSP": "IBM", "data_type": "metrics", "error": null, "governance_data": {"memory_usage": 36.6, "cpu_usage": 3.0, "disk_usage": 4.2, "bytes_sent": 2702424, "bytes_recv": 7195543, "additional_metric_1": "value_1", "additional_metric_2": "value_2"}, "log_id": "d49b50b3-7c34-475f-8c62-659703a5776a", "service_name": "cna-app", "timestamps": {"cna_timestamp": "2024-08-12T17:27:13.047954+00:00", "RG_GOV_IMS_API_Gateway_timestamp": "2024-08-12T17:27:13.131895+00:00", "RG_GOV_IMS_Converter_timestamp": "2024-08-12T17:27:13.252024+00:00", "RG_GOV_IMS_Archiver_timestamp": "2024-08-12T17:27:13.361460+00:00"}}