{"CSP": "IBM", "data_type": "metrics", "error": null, "governance_data": {"memory_usage": 36.6, "cpu_usage": 7.6, "disk_usage": 4.2, "bytes_sent": 5895976, "bytes_recv": 15699167, "additional_metric_1": "value_1", "additional_metric_2": "value_2"}, "log_id": "2deb6049-3e7a-495e-8ff6-15a9c388bdf7", "service_name": "cna-app", "timestamps": {"cna_timestamp": "2024-08-12T17:45:48.689791+00:00", "RG_GOV_IMS_API_Gateway_timestamp": "2024-08-12T17:45:48.760176+00:00", "RG_GOV_IMS_Converter_timestamp": "2024-08-12T17:45:48.848341+00:00", "RG_GOV_IMS_Archiver_timestamp": "2024-08-12T17:45:48.951019+00:00"}}