{"CSP": "IBM", "data_type": "metrics", "error": null, "governance_data": {"memory_usage": 36.2, "cpu_usage": 13.1, "disk_usage": 4.2, "bytes_sent": 3021631, "bytes_recv": 8046785, "additional_metric_1": "value_1", "additional_metric_2": "value_2"}, "log_id": "29fb6842-48b9-4bf9-96c1-7035cd8dda6c", "service_name": "cna-app", "timestamps": {"cna_timestamp": "2024-08-12T17:29:04.918505+00:00", "RG_GOV_IMS_API_Gateway_timestamp": "2024-08-12T17:29:04.988888+00:00", "RG_GOV_IMS_Converter_timestamp": "2024-08-12T17:29:05.070360+00:00", "RG_GOV_IMS_Archiver_timestamp": "2024-08-12T17:29:05.153668+00:00"}}