{"CSP": "IBM", "data_type": "metrics", "error": null, "governance_data": {"memory_usage": 36.6, "cpu_usage": 5.1, "disk_usage": 4.2, "bytes_sent": 4560746, "bytes_recv": 12142399, "additional_metric_1": "value_1", "additional_metric_2": "value_2"}, "log_id": "ac92a92e-db4a-41ba-a06a-a44ae11b0d3b", "service_name": "cna-app", "timestamps": {"cna_timestamp": "2024-08-12T17:38:02.448677+00:00", "RG_GOV_IMS_API_Gateway_timestamp": "2024-08-12T17:38:02.614024+00:00", "RG_GOV_IMS_Converter_timestamp": "2024-08-12T17:38:02.710083+00:00", "RG_GOV_IMS_Archiver_timestamp": "2024-08-12T17:38:02.793758+00:00"}}