{"CSP": "IBM", "data_type": "metrics", "error": null, "governance_data": {"memory_usage": 36.5, "cpu_usage": 3.0, "disk_usage": 4.2, "bytes_sent": 1891598, "bytes_recv": 5036569, "additional_metric_1": "value_1", "additional_metric_2": "value_2"}, "log_id": "fd3463be-925b-460d-940b-d5a066c98f4e", "service_name": "cna-app", "timestamps": {"cna_timestamp": "2024-08-12T17:22:29.370554+00:00", "RG_GOV_IMS_API_Gateway_timestamp": "2024-08-12T17:22:29.440672+00:00", "RG_GOV_IMS_Converter_timestamp": "2024-08-12T17:22:29.529964+00:00", "RG_GOV_IMS_Archiver_timestamp": "2024-08-12T17:22:29.656032+00:00"}}