{"CSP": "IBM", "data_type": "metrics", "error": null, "governance_data": {"memory_usage": 36.3, "cpu_usage": 2.5, "disk_usage": 4.2, "bytes_sent": 639442, "bytes_recv": 1699380, "additional_metric_1": "value_1", "additional_metric_2": "value_2"}, "log_id": "a38462d6-673d-47f2-ad56-6378e282cd43", "service_name": "cna-app", "timestamps": {"cna_timestamp": "2024-08-12T17:15:12.153089+00:00", "RG_GOV_IMS_API_Gateway_timestamp": "2024-08-12T17:15:12.223231+00:00", "RG_GOV_IMS_Converter_timestamp": "2024-08-12T17:15:12.796626+00:00", "RG_GOV_IMS_Archiver_timestamp": "2024-08-12T17:15:12.885232+00:00"}}