{"CSP": "IBM", "data_type": "metrics", "error": null, "governance_data": {"memory_usage": 36.6, "cpu_usage": 9.5, "disk_usage": 4.2, "bytes_sent": 5838394, "bytes_recv": 15545663, "additional_metric_1": "value_1", "additional_metric_2": "value_2"}, "log_id": "5d01430a-5d3e-430f-815c-5a4d787c9a3f", "service_name": "cna-app", "timestamps": {"cna_timestamp": "2024-08-12T17:45:28.710706+00:00", "RG_GOV_IMS_API_Gateway_timestamp": "2024-08-12T17:45:28.799075+00:00", "RG_GOV_IMS_Converter_timestamp": "2024-08-12T17:45:28.888523+00:00", "RG_GOV_IMS_Archiver_timestamp": "2024-08-12T17:45:28.992340+00:00"}}