{"CSP": "IBM", "data_type": "metrics", "error": null, "governance_data": {"memory_usage": 36.5, "cpu_usage": 2.6, "disk_usage": 4.2, "bytes_sent": 2989631, "bytes_recv": 7961991, "additional_metric_1": "value_1", "additional_metric_2": "value_2"}, "log_id": "5f69fcfa-3016-45a5-9931-64034a30c834", "service_name": "cna-app", "timestamps": {"cna_timestamp": "2024-08-12T17:28:53.786287+00:00", "RG_GOV_IMS_API_Gateway_timestamp": "2024-08-12T17:28:53.866501+00:00", "RG_GOV_IMS_Converter_timestamp": "2024-08-12T17:28:53.994255+00:00", "RG_GOV_IMS_Archiver_timestamp": "2024-08-12T17:28:54.086365+00:00"}}