{"CSP": "IBM", "data_type": "metrics", "error": null, "governance_data": {"memory_usage": 36.6, "cpu_usage": 3.6, "disk_usage": 4.2, "bytes_sent": 2453657, "bytes_recv": 6533911, "additional_metric_1": "value_1", "additional_metric_2": "value_2"}, "log_id": "4cff27a4-5397-4b23-90bb-af243d51abe6", "service_name": "cna-app", "timestamps": {"cna_timestamp": "2024-08-12T17:25:46.066275+00:00", "RG_GOV_IMS_API_Gateway_timestamp": "2024-08-12T17:25:46.138635+00:00", "RG_GOV_IMS_Converter_timestamp": "2024-08-12T17:25:46.227258+00:00", "RG_GOV_IMS_Archiver_timestamp": "2024-08-12T17:25:46.297217+00:00"}}