{"CSP": "IBM", "data_type": "metrics", "error": null, "governance_data": {"memory_usage": 36.4, "cpu_usage": 2.0, "disk_usage": 4.2, "bytes_sent": 4969886, "bytes_recv": 13233675, "additional_metric_1": "value_1", "additional_metric_2": "value_2"}, "log_id": "5c7472aa-4266-49ea-bf3c-0317808931ed", "service_name": "cna-app", "timestamps": {"cna_timestamp": "2024-08-12T17:40:25.286102+00:00", "RG_GOV_IMS_API_Gateway_timestamp": "2024-08-12T17:40:25.354014+00:00", "RG_GOV_IMS_Converter_timestamp": "2024-08-12T17:40:25.435241+00:00", "RG_GOV_IMS_Archiver_timestamp": "2024-08-12T17:40:25.523891+00:00"}}