{"CSP": "AWS", "data_type": "metrics", "error": null, "governance_data": {"memory_usage": 37.1, "cpu_usage": 0.5, "disk_usage": 34.3, "bytes_sent": 1128365, "bytes_recv": 61184240, "additional_metric_1": "value_1", "additional_metric_2": "value_2"}, "log_id": "fc3cb7a2-ae18-477a-acab-cce8425d49fc", "service_name": "cna-app", "timestamps": {"cna_timestamp": "2024-09-06T14:19:49.929743+00:00", "RG_1_API_Gateway_timestamp": "2024-09-06T14:19:49.950571+00:00", "RG_1_SQS_Forwarder_timestamp": "2024-09-06T14:19:49.992683+00:00", "RG_GOV_IMS_API_Gateway_timestamp": "2024-09-06T14:19:50.782905+00:00", "RG_GOV_IMS_Converter_timestamp": "2024-09-06T14:19:50.868023+00:00", "RG_GOV_IMS_Archiver_timestamp": "2024-09-06T14:19:51.365938+00:00"}}