{"CSP": "AWS", "data_type": "metrics", "error": null, "governance_data": {"memory_usage": 36.9, "cpu_usage": 2.5, "disk_usage": 34.3, "bytes_sent": 301180, "bytes_recv": 58700258, "additional_metric_1": "value_1", "additional_metric_2": "value_2"}, "log_id": "f25262dd-15e7-44cb-93dd-cdd86b594292", "service_name": "cna-app", "timestamps": {"cna_timestamp": "2024-09-06T14:13:39.969696+00:00", "RG_1_API_Gateway_timestamp": "2024-09-06T14:13:39.989385+00:00", "RG_1_SQS_Forwarder_timestamp": "2024-09-06T14:13:40.040931+00:00", "RG_GOV_IMS_API_Gateway_timestamp": "2024-09-06T14:13:40.819928+00:00", "RG_GOV_IMS_Converter_timestamp": "2024-09-06T14:13:40.906728+00:00", "RG_GOV_IMS_Archiver_timestamp": "2024-09-06T14:13:40.990324+00:00"}}