{"CSP": "AWS", "data_type": "metrics", "error": null, "governance_data": {"memory_usage": 37.6, "cpu_usage": 1.0, "disk_usage": 34.3, "bytes_sent": 8868039, "bytes_recv": 84387425, "additional_metric_1": "value_1", "additional_metric_2": "value_2"}, "log_id": "a938a73d-84ba-4268-97fa-60124b88e12e", "service_name": "cna-app", "timestamps": {"cna_timestamp": "2024-09-06T15:17:24.648440+00:00", "RG_1_API_Gateway_timestamp": "2024-09-06T15:17:24.675654+00:00", "RG_1_SQS_Forwarder_timestamp": "2024-09-06T15:17:24.727490+00:00", "RG_GOV_IMS_API_Gateway_timestamp": "2024-09-06T15:17:25.520684+00:00", "RG_GOV_IMS_Converter_timestamp": "2024-09-06T15:17:25.609447+00:00", "RG_GOV_IMS_Archiver_timestamp": "2024-09-06T15:17:25.709562+00:00"}}