{"CSP": "AWS", "data_type": "metrics", "error": null, "governance_data": {"memory_usage": 37.5, "cpu_usage": 0.5, "disk_usage": 34.3, "bytes_sent": 6836911, "bytes_recv": 78291799, "additional_metric_1": "value_1", "additional_metric_2": "value_2"}, "log_id": "c15cddd4-99d8-48c1-869e-539967a2643f", "service_name": "cna-app", "timestamps": {"cna_timestamp": "2024-09-06T15:02:17.961619+00:00", "RG_1_API_Gateway_timestamp": "2024-09-06T15:02:17.993352+00:00", "RG_1_SQS_Forwarder_timestamp": "2024-09-06T15:02:18.041563+00:00", "RG_GOV_IMS_API_Gateway_timestamp": "2024-09-06T15:02:18.831395+00:00", "RG_GOV_IMS_Converter_timestamp": "2024-09-06T15:02:18.911323+00:00", "RG_GOV_IMS_Archiver_timestamp": "2024-09-06T15:02:19.001280+00:00"}}