{"CSP": "AWS", "data_type": "metrics", "error": null, "governance_data": {"memory_usage": 37.5, "cpu_usage": 1.0, "disk_usage": 34.3, "bytes_sent": 8253295, "bytes_recv": 82543829, "additional_metric_1": "value_1", "additional_metric_2": "value_2"}, "log_id": "aaaec330-ebcb-4954-b682-b0840f6b5377", "service_name": "cna-app", "timestamps": {"cna_timestamp": "2024-09-06T15:12:50.096647+00:00", "RG_1_API_Gateway_timestamp": "2024-09-06T15:12:50.119744+00:00", "RG_1_SQS_Forwarder_timestamp": "2024-09-06T15:12:50.170768+00:00", "RG_GOV_IMS_API_Gateway_timestamp": "2024-09-06T15:12:50.957002+00:00", "RG_GOV_IMS_Converter_timestamp": "2024-09-06T15:12:51.136802+00:00", "RG_GOV_IMS_Archiver_timestamp": "2024-09-06T15:12:51.221016+00:00"}}