{"CSP": "AWS", "data_type": "metrics", "error": null, "governance_data": {"memory_usage": 37.7, "cpu_usage": 0.5, "disk_usage": 34.3, "bytes_sent": 11853313, "bytes_recv": 93331223, "additional_metric_1": "value_1", "additional_metric_2": "value_2"}, "log_id": "b19994a7-ad3a-4cbe-b03b-741ec81f4701", "service_name": "cna-app", "timestamps": {"cna_timestamp": "2024-09-06T15:39:37.229730+00:00", "RG_1_API_Gateway_timestamp": "2024-09-06T15:39:37.247987+00:00", "RG_1_SQS_Forwarder_timestamp": "2024-09-06T15:39:37.290165+00:00", "RG_GOV_IMS_API_Gateway_timestamp": "2024-09-06T15:39:37.998761+00:00", "RG_GOV_IMS_Converter_timestamp": "2024-09-06T15:39:38.176958+00:00", "RG_GOV_IMS_Archiver_timestamp": "2024-09-06T15:39:38.282026+00:00"}}