{"CSP": "AWS", "data_type": "metrics", "error": null, "governance_data": {"memory_usage": 37.1, "cpu_usage": 0.0, "disk_usage": 34.3, "bytes_sent": 452442, "bytes_recv": 59154530, "additional_metric_1": "value_1", "additional_metric_2": "value_2"}, "log_id": "d12336f6-fee8-4ca4-89d7-229cffa9aea6", "service_name": "cna-app", "timestamps": {"cna_timestamp": "2024-09-06T14:14:47.671725+00:00", "RG_1_API_Gateway_timestamp": "2024-09-06T14:14:47.692250+00:00", "RG_1_SQS_Forwarder_timestamp": "2024-09-06T14:14:47.766433+00:00", "RG_GOV_IMS_API_Gateway_timestamp": "2024-09-06T14:14:48.537848+00:00", "RG_GOV_IMS_Converter_timestamp": "2024-09-06T14:14:48.605758+00:00", "RG_GOV_IMS_Archiver_timestamp": "2024-09-06T14:14:48.687868+00:00"}}