{"CSP": "AWS", "data_type": "metrics", "error": null, "governance_data": {"memory_usage": 37.7, "cpu_usage": 3.0, "disk_usage": 34.3, "bytes_sent": 10613345, "bytes_recv": 89619547, "additional_metric_1": "value_1", "additional_metric_2": "value_2"}, "log_id": "f1aa7b3d-c13e-4dde-ae43-561a732ee1f7", "service_name": "cna-app", "timestamps": {"cna_timestamp": "2024-09-06T15:30:24.592482+00:00", "RG_1_API_Gateway_timestamp": "2024-09-06T15:30:24.617878+00:00", "RG_1_SQS_Forwarder_timestamp": "2024-09-06T15:30:24.667770+00:00", "RG_GOV_IMS_API_Gateway_timestamp": "2024-09-06T15:30:25.450165+00:00", "RG_GOV_IMS_Converter_timestamp": "2024-09-06T15:30:25.551385+00:00", "RG_GOV_IMS_Archiver_timestamp": "2024-09-06T15:30:25.636298+00:00"}}