{"CSP": "IBM", "data_type": "logs", "error": null, "governance_data": {"log_1": "Application started successfully.", "log_2": "Collecting system metrics.", "log_3": "Metrics collected successfully.", "log_4": "Sending data to API Gateway.", "log_5": "Data sent successfully.", "log_6": "Error handling and logging mechanism operational.", "log_7": "System monitoring and logging active.", "log_8": "Routine check completed successfully.", "log_9": "No errors detected in the last cycle.", "log_10": "All systems functional."}, "log_id": "eee033b9-52f0-484d-99b3-eeccd840fb83", "service_name": "cna-app", "timestamps": {"cna_timestamp": "2024-08-12T17:15:05.552129+00:00", "RG_GOV_IMS_API_Gateway_timestamp": "2024-08-12T17:15:05.622408+00:00", "RG_GOV_IMS_Converter_timestamp": "2024-08-12T17:15:05.709987+00:00", "RG_GOV_IMS_Archiver_timestamp": "2024-08-12T17:15:05.806756+00:00"}}